{"version":1,"meta":{"name":"Platform5","savedAt":"2026-05-13T19:31:42.819Z"},"root":"UdNFICK8So07b7TD6UWdg","objects":[{"uuid":"UdNFICK8So07b7TD6UWdg","name":"Platform5","parent":null,"transform":{"position":[28.442172438667626,31.0874521757855,-1052.8254158779198],"rotation":[-1.5530354100472946e-12,1.5707963267948966,0],"scale":[25.413916247759516,5.177201036966238,144.59522077211474]},"active":true,"layer":"Default","tag":"Untagged","components":[{"type":"MeshRenderer","pack":"core","packVersion":"0.0.0","enabled":true,"props":{"castShadow":true,"material":"materials/black","primitive":"Cube","receiveShadow":true}},{"type":"BoxCollider","pack":"physics-rapier","packVersion":"0.0.0","enabled":true,"props":{"density":1,"friction":0.5,"isTrigger":false,"layer":"Default","offset":[0,0,0],"restitution":0,"size":[1,1,1]}}],"static":false},{"uuid":"1dcVTMIoz7Zlo0sjtsywG","name":"Platform4","parent":"UdNFICK8So07b7TD6UWdg","transform":{"position":[4.405364961712621e-13,-1.3904539554509743,-0.009090424145071302],"rotation":[-1.4100655971839263e-27,0,0],"scale":[1,1.7835782461291856,1.0167691156979146]},"active":true,"layer":"Default","tag":"Untagged","components":[{"type":"MeshRenderer","pack":"core","packVersion":"0.0.0","enabled":true,"props":{"castShadow":true,"material":"materials/Home/GraySt2","primitive":"Cube","receiveShadow":true}},{"type":"BoxCollider","pack":"physics-rapier","packVersion":"0.0.0","enabled":true,"props":{"density":1,"friction":0.5,"isTrigger":false,"layer":"Default","offset":[0,0,0],"restitution":0,"size":[1,1,1]}}],"static":false},{"uuid":"pd1W8t4M5MzaOT3m_HKpZ","name":"Platform4","parent":"UdNFICK8So07b7TD6UWdg","transform":{"position":[0.21300328208726427,-1.2141176608183954,0.28856662334169775],"rotation":[-1.4100655971839274e-27,0,0],"scale":[1.5954913182580173,2.136250835392114,0.1770931924455978]},"active":true,"layer":"Default","tag":"Untagged","components":[{"type":"MeshRenderer","pack":"core","packVersion":"0.0.0","enabled":true,"props":{"castShadow":true,"material":"materials/platform/platform_wall","primitive":"Cube","receiveShadow":true}},{"type":"BoxCollider","pack":"physics-rapier","packVersion":"0.0.0","enabled":true,"props":{"density":1,"friction":0.5,"isTrigger":false,"layer":"Default","offset":[0,0,0],"restitution":0,"size":[1,1,1]}}],"static":false},{"uuid":"seLfxJK-tZv76o1SbhkDT","name":"Platform4","parent":"UdNFICK8So07b7TD6UWdg","transform":{"position":[0.039666963221989704,-1.9003172034909275,-0.04000258906959725],"rotation":[-1.410065597183927e-27,0,0],"scale":[1.6786580648194285,1.6617911957802791,0.21233060963481412]},"active":true,"layer":"Default","tag":"Untagged","components":[{"type":"MeshRenderer","pack":"core","packVersion":"0.0.0","enabled":true,"props":{"castShadow":true,"material":"materials/Home/GraySt1","primitive":"Cube","receiveShadow":true}},{"type":"BoxCollider","pack":"physics-rapier","packVersion":"0.0.0","enabled":true,"props":{"density":1,"friction":0.5,"isTrigger":false,"layer":"Default","offset":[0,0,0],"restitution":0,"size":[1,1,1]}}],"static":false},{"uuid":"Ur92yct4-6PCIhUfT0fnv","name":"Platform4","parent":"UdNFICK8So07b7TD6UWdg","transform":{"position":[-0.020966882749718252,-1.540930514849598,-0.37178453211928064],"rotation":[-1.4100655971839258e-27,0,0],"scale":[1.221858867769728,1.4785486074825125,0.19877665545434667]},"active":true,"layer":"Default","tag":"Untagged","components":[{"type":"MeshRenderer","pack":"core","packVersion":"0.0.0","enabled":true,"props":{"castShadow":true,"material":"materials/black","primitive":"Cube","receiveShadow":true}},{"type":"BoxCollider","pack":"physics-rapier","packVersion":"0.0.0","enabled":true,"props":{"density":1,"friction":0.5,"isTrigger":false,"layer":"Default","offset":[0,0,0],"restitution":0,"size":[1,1,1]}}],"static":false},{"uuid":"_AvfLFWTPbEq-V52knO-9","name":"Platform4","parent":"UdNFICK8So07b7TD6UWdg","transform":{"position":[0.26131374173643707,0.706269356382144,0.016295675602462173],"rotation":[1.5707963267948284,3.969401734188916e-12,3.6530700485328295e-12],"scale":[1.6008750355342416,1.1120413088398553,0.7545591730971568]},"active":true,"layer":"Default","tag":"Untagged","components":[{"type":"MeshRenderer","pack":"core","packVersion":"0.0.0","enabled":true,"props":{"castShadow":true,"material":"materials/black","primitive":"Cube","receiveShadow":true}},{"type":"BoxCollider","pack":"physics-rapier","packVersion":"0.0.0","enabled":true,"props":{"density":1,"friction":0.5,"isTrigger":false,"layer":"Default","offset":[0,0,0],"restitution":0,"size":[1,1,1]}}],"static":false}]}